{
	"$schema": "http://schema.management.azure.com/schemas/2015-01-01/deploymentTemplate.json#",
	"contentVersion": "1.0.0.0",
	"parameters": {
		"factoryName": {
			"type": "string",
			"metadata": "Data Factory name",
			"defaultValue": "ADFUniversalOrchestratorFramework"
		},
		"lk_blob_cedc_new_connectionString": {
			"type": "secureString",
			"metadata": "Secure string for 'connectionString' of 'lk_blob_cedc_new'"
		},
		"lk_dl_cedc_2_accountKey": {
			"type": "secureString",
			"metadata": "Secure string for 'accountKey' of 'lk_dl_cedc_2'"
		},
		"AKVLinkedService_UniversalOrchestratorFramework_properties_typeProperties_baseUrl": {
			"type": "string",
			"defaultValue": "https://adf-framework.vault.azure.net/"
		},
		"lk_dl_cedc_properties_typeProperties_url": {
			"type": "string",
			"defaultValue": "https://cedcdatalake.dfs.core.windows.net/"
		},
		"lk_dl_cedc_2_properties_typeProperties_url": {
			"type": "string",
			"defaultValue": "https://cedcdatalake.dfs.core.windows.net/"
		}
	},
	"variables": {
		"factoryId": "[concat('Microsoft.DataFactory/factories/', parameters('factoryName'))]"
	},
	"resources": [
		{
			"name": "[concat(parameters('factoryName'), '/task_call_databricks')]",
			"type": "Microsoft.DataFactory/factories/pipelines",
			"apiVersion": "2018-06-01",
			"properties": {
				"activities": [
					{
						"name": "Wait1",
						"type": "Wait",
						"dependsOn": [],
						"userProperties": [],
						"typeProperties": {
							"waitTimeInSeconds": 1
						}
					}
				],
				"policy": {
					"elapsedTimeMetric": {}
				},
				"folder": {
					"name": "ADFUniversalOrchestratorFramework/99_Workers"
				},
				"annotations": [],
				"lastPublishTime": "2024-07-13T02:37:12Z"
			},
			"dependsOn": []
		},
		{
			"name": "[concat(parameters('factoryName'), '/task_proj1_api_dm')]",
			"type": "Microsoft.DataFactory/factories/pipelines",
			"apiVersion": "2018-06-01",
			"properties": {
				"description": "Used just so the metadata has something to call during development.",
				"activities": [
					{
						"name": "Wait5",
						"description": "Framework development worker simulator.",
						"type": "Wait",
						"dependsOn": [],
						"userProperties": [],
						"typeProperties": {
							"waitTimeInSeconds": {
								"value": "@pipeline().parameters.WaitTime",
								"type": "Expression"
							}
						}
					}
				],
				"policy": {
					"elapsedTimeMetric": {}
				},
				"parameters": {
					"WaitTime": {
						"type": "int",
						"defaultValue": 5
					}
				},
				"folder": {
					"name": "ADFUniversalOrchestratorFramework/99_Workers"
				},
				"annotations": [
					"_metadataWorker"
				],
				"lastPublishTime": "2024-07-13T02:37:12Z"
			},
			"dependsOn": []
		},
		{
			"name": "[concat(parameters('factoryName'), '/task_proj1_api_dm2')]",
			"type": "Microsoft.DataFactory/factories/pipelines",
			"apiVersion": "2018-06-01",
			"properties": {
				"description": "Used just so the metadata has something to call during development.",
				"activities": [
					{
						"name": "Wait7",
						"description": "Framework development worker simulator.",
						"type": "Wait",
						"dependsOn": [],
						"userProperties": [],
						"typeProperties": {
							"waitTimeInSeconds": {
								"value": "@pipeline().parameters.WaitTime",
								"type": "Expression"
							}
						}
					}
				],
				"policy": {
					"elapsedTimeMetric": {}
				},
				"parameters": {
					"WaitTime": {
						"type": "int",
						"defaultValue": 5
					}
				},
				"folder": {
					"name": "ADFUniversalOrchestratorFramework/99_Workers"
				},
				"annotations": [
					"_metadataWorker"
				],
				"lastPublishTime": "2024-07-13T02:37:12Z"
			},
			"dependsOn": []
		},
		{
			"name": "[concat(parameters('factoryName'), '/task_proj1_api_edw')]",
			"type": "Microsoft.DataFactory/factories/pipelines",
			"apiVersion": "2018-06-01",
			"properties": {
				"description": "Used just so the metadata has something to call during development.",
				"activities": [
					{
						"name": "Wait4",
						"description": "Framework development worker simulator.",
						"type": "Wait",
						"dependsOn": [],
						"userProperties": [],
						"typeProperties": {
							"waitTimeInSeconds": {
								"value": "@pipeline().parameters.WaitTime",
								"type": "Expression"
							}
						}
					}
				],
				"policy": {
					"elapsedTimeMetric": {}
				},
				"parameters": {
					"WaitTime": {
						"type": "int",
						"defaultValue": 5
					}
				},
				"folder": {
					"name": "ADFUniversalOrchestratorFramework/99_Workers"
				},
				"annotations": [
					"_metadataWorker"
				],
				"lastPublishTime": "2024-07-13T02:37:12Z"
			},
			"dependsOn": []
		},
		{
			"name": "[concat(parameters('factoryName'), '/task_proj1_api_interim')]",
			"type": "Microsoft.DataFactory/factories/pipelines",
			"apiVersion": "2018-06-01",
			"properties": {
				"description": "Used just so the metadata has something to call during development.",
				"activities": [
					{
						"name": "Wait3",
						"description": "Framework development worker simulator.",
						"type": "Wait",
						"dependsOn": [],
						"userProperties": [],
						"typeProperties": {
							"waitTimeInSeconds": {
								"value": "@pipeline().parameters.WaitTime",
								"type": "Expression"
							}
						}
					}
				],
				"policy": {
					"elapsedTimeMetric": {}
				},
				"parameters": {
					"WaitTime": {
						"type": "int",
						"defaultValue": 5
					}
				},
				"folder": {
					"name": "ADFUniversalOrchestratorFramework/99_Workers"
				},
				"annotations": [
					"_metadataWorker"
				],
				"lastPublishTime": "2024-07-13T02:37:12Z"
			},
			"dependsOn": []
		},
		{
			"name": "[concat(parameters('factoryName'), '/task_proj1_api_landing')]",
			"type": "Microsoft.DataFactory/factories/pipelines",
			"apiVersion": "2018-06-01",
			"properties": {
				"description": "Used just so the metadata has something to call during development.",
				"activities": [
					{
						"name": "Wait1",
						"description": "Framework development worker simulator.",
						"type": "Wait",
						"dependsOn": [],
						"userProperties": [],
						"typeProperties": {
							"waitTimeInSeconds": {
								"value": "@pipeline().parameters.WaitTime",
								"type": "Expression"
							}
						}
					}
				],
				"policy": {
					"elapsedTimeMetric": {}
				},
				"parameters": {
					"WaitTime": {
						"type": "int",
						"defaultValue": 2
					}
				},
				"folder": {
					"name": "ADFUniversalOrchestratorFramework/99_Workers"
				},
				"annotations": [
					"_metadataWorker"
				],
				"lastPublishTime": "2024-07-13T02:37:12Z"
			},
			"dependsOn": []
		},
		{
			"name": "[concat(parameters('factoryName'), '/task_proj1_api_malformed')]",
			"type": "Microsoft.DataFactory/factories/pipelines",
			"apiVersion": "2018-06-01",
			"properties": {
				"description": "Used just so the metadata has something to call during development.",
				"activities": [
					{
						"name": "Wait2",
						"description": "Framework development worker simulator.",
						"type": "Wait",
						"dependsOn": [],
						"userProperties": [],
						"typeProperties": {
							"waitTimeInSeconds": {
								"value": "@pipeline().parameters.WaitTime",
								"type": "Expression"
							}
						}
					}
				],
				"policy": {
					"elapsedTimeMetric": {}
				},
				"parameters": {
					"WaitTime": {
						"type": "int",
						"defaultValue": 5
					}
				},
				"folder": {
					"name": "ADFUniversalOrchestratorFramework/99_Workers"
				},
				"annotations": [
					"_metadataWorker"
				],
				"lastPublishTime": "2024-07-13T02:37:12Z"
			},
			"dependsOn": []
		},
		{
			"name": "[concat(parameters('factoryName'), '/task_proj1_api_speed')]",
			"type": "Microsoft.DataFactory/factories/pipelines",
			"apiVersion": "2018-06-01",
			"properties": {
				"description": "Used just so the metadata has something to call during development.",
				"activities": [
					{
						"name": "Wait6",
						"description": "Framework development worker simulator.",
						"type": "Wait",
						"dependsOn": [],
						"userProperties": [],
						"typeProperties": {
							"waitTimeInSeconds": {
								"value": "@pipeline().parameters.WaitTime",
								"type": "Expression"
							}
						}
					},
					{
						"name": "Fail Pipe6 to test",
						"type": "Fail",
						"state": "Inactive",
						"onInactiveMarkAs": "Succeeded",
						"dependsOn": [
							{
								"activity": "Wait6",
								"dependencyConditions": [
									"Succeeded"
								]
							}
						],
						"userProperties": [],
						"typeProperties": {
							"message": "\"test dependency failed Wait 6\"",
							"errorCode": "404"
						}
					}
				],
				"policy": {
					"elapsedTimeMetric": {}
				},
				"parameters": {
					"WaitTime": {
						"type": "int",
						"defaultValue": 5
					}
				},
				"folder": {
					"name": "ADFUniversalOrchestratorFramework/99_Workers"
				},
				"annotations": [
					"_metadataWorker"
				],
				"lastPublishTime": "2024-07-13T02:37:12Z"
			},
			"dependsOn": []
		},
		{
			"name": "[concat(parameters('factoryName'), '/AKVLinkedService_UniversalOrchestratorFramework')]",
			"type": "Microsoft.DataFactory/factories/linkedServices",
			"apiVersion": "2018-06-01",
			"properties": {
				"annotations": [],
				"type": "AzureKeyVault",
				"typeProperties": {
					"baseUrl": "[parameters('AKVLinkedService_UniversalOrchestratorFramework_properties_typeProperties_baseUrl')]"
				}
			},
			"dependsOn": []
		},
		{
			"name": "[concat(parameters('factoryName'), '/lk_blob_cedc_new')]",
			"type": "Microsoft.DataFactory/factories/linkedServices",
			"apiVersion": "2018-06-01",
			"properties": {
				"annotations": [],
				"type": "AzureBlobStorage",
				"typeProperties": {
					"connectionString": "[parameters('lk_blob_cedc_new_connectionString')]"
				}
			},
			"dependsOn": []
		},
		{
			"name": "[concat(parameters('factoryName'), '/lk_dl_cedc')]",
			"type": "Microsoft.DataFactory/factories/linkedServices",
			"apiVersion": "2018-06-01",
			"properties": {
				"annotations": [],
				"type": "AzureBlobFS",
				"typeProperties": {
					"url": "[parameters('lk_dl_cedc_properties_typeProperties_url')]"
				}
			},
			"dependsOn": []
		},
		{
			"name": "[concat(parameters('factoryName'), '/lk_dl_cedc_2')]",
			"type": "Microsoft.DataFactory/factories/linkedServices",
			"apiVersion": "2018-06-01",
			"properties": {
				"annotations": [],
				"type": "AzureBlobFS",
				"typeProperties": {
					"url": "[parameters('lk_dl_cedc_2_properties_typeProperties_url')]",
					"accountKey": {
						"type": "SecureString",
						"value": "[parameters('lk_dl_cedc_2_accountKey')]"
					}
				}
			},
			"dependsOn": []
		},
		{
			"name": "[concat(parameters('factoryName'), '/LUYAN')]",
			"type": "Microsoft.DataFactory/factories/integrationRuntimes",
			"apiVersion": "2018-06-01",
			"properties": {
				"type": "SelfHosted",
				"typeProperties": {}
			},
			"dependsOn": []
		},
		{
			"name": "[concat(parameters('factoryName'), '/SelfHostedIR-Windows-LiuYang')]",
			"type": "Microsoft.DataFactory/factories/integrationRuntimes",
			"apiVersion": "2018-06-01",
			"properties": {
				"type": "SelfHosted",
				"typeProperties": {}
			},
			"dependsOn": []
		},
		{
			"name": "[concat(parameters('factoryName'), '/SelfHostedIR-Windows')]",
			"type": "Microsoft.DataFactory/factories/integrationRuntimes",
			"apiVersion": "2018-06-01",
			"properties": {
				"type": "SelfHosted",
				"typeProperties": {}
			},
			"dependsOn": []
		},
		{
			"name": "[concat(parameters('factoryName'), '/CSV_COPY_BLOB_GEN2_m8j_DestinationDS')]",
			"type": "Microsoft.DataFactory/factories/datasets",
			"apiVersion": "2018-06-01",
			"properties": {
				"linkedServiceName": {
					"referenceName": "lk_dl_cedc_2",
					"type": "LinkedServiceReference"
				},
				"parameters": {
					"cw_columnDelimiter": {
						"type": "String"
					},
					"cw_escapeChar": {
						"type": "String"
					},
					"cw_quoteChar": {
						"type": "String"
					},
					"cw_firstRowAsHeader": {
						"type": "Bool"
					},
					"cw_fileName": {
						"type": "String"
					},
					"cw_folderPath": {
						"type": "String"
					},
					"cw_fileSystem": {
						"type": "String"
					}
				},
				"folder": {
					"name": "CSV_COPY_BLOB_GEN2_m8j_20240715"
				},
				"annotations": [],
				"type": "DelimitedText",
				"typeProperties": {
					"location": {
						"type": "AzureBlobFSLocation",
						"fileName": {
							"value": "@dataset().cw_fileName",
							"type": "Expression"
						},
						"folderPath": {
							"value": "@dataset().cw_folderPath",
							"type": "Expression"
						},
						"fileSystem": {
							"value": "@dataset().cw_fileSystem",
							"type": "Expression"
						}
					},
					"columnDelimiter": {
						"value": "@dataset().cw_columnDelimiter",
						"type": "Expression"
					},
					"escapeChar": {
						"value": "@dataset().cw_escapeChar",
						"type": "Expression"
					},
					"firstRowAsHeader": {
						"value": "@dataset().cw_firstRowAsHeader",
						"type": "Expression"
					},
					"quoteChar": {
						"value": "@dataset().cw_quoteChar",
						"type": "Expression"
					}
				},
				"schema": []
			},
			"dependsOn": [
				"[concat(variables('factoryId'), '/linkedServices/lk_dl_cedc_2')]"
			]
		},
		{
			"name": "[concat(parameters('factoryName'), '/CSV_COPY_BLOB_GEN2_m8j_SourceDS')]",
			"type": "Microsoft.DataFactory/factories/datasets",
			"apiVersion": "2018-06-01",
			"properties": {
				"linkedServiceName": {
					"referenceName": "lk_blob_cedc_new",
					"type": "LinkedServiceReference"
				},
				"parameters": {
					"cw_columnDelimiter": {
						"type": "String"
					},
					"cw_escapeChar": {
						"type": "String"
					},
					"cw_quoteChar": {
						"type": "String"
					},
					"cw_firstRowAsHeader": {
						"type": "Bool"
					},
					"cw_fileName": {
						"type": "String"
					},
					"cw_folderPath": {
						"type": "String"
					},
					"cw_container": {
						"type": "String"
					}
				},
				"folder": {
					"name": "CSV_COPY_BLOB_GEN2_m8j_20240715"
				},
				"annotations": [],
				"type": "DelimitedText",
				"typeProperties": {
					"location": {
						"type": "AzureBlobStorageLocation",
						"fileName": {
							"value": "@dataset().cw_fileName",
							"type": "Expression"
						},
						"folderPath": {
							"value": "@dataset().cw_folderPath",
							"type": "Expression"
						},
						"container": {
							"value": "@dataset().cw_container",
							"type": "Expression"
						}
					},
					"columnDelimiter": {
						"value": "@dataset().cw_columnDelimiter",
						"type": "Expression"
					},
					"escapeChar": {
						"value": "@dataset().cw_escapeChar",
						"type": "Expression"
					},
					"firstRowAsHeader": {
						"value": "@dataset().cw_firstRowAsHeader",
						"type": "Expression"
					},
					"quoteChar": {
						"value": "@dataset().cw_quoteChar",
						"type": "Expression"
					}
				},
				"schema": []
			},
			"dependsOn": [
				"[concat(variables('factoryId'), '/linkedServices/lk_blob_cedc_new')]"
			]
		},
		{
			"name": "[concat(parameters('factoryName'), '/MetadataDrivenCopyTask_5hq_DestinationDS')]",
			"type": "Microsoft.DataFactory/factories/datasets",
			"apiVersion": "2018-06-01",
			"properties": {
				"linkedServiceName": {
					"referenceName": "lk_dl_cedc_2",
					"type": "LinkedServiceReference"
				},
				"parameters": {
					"cw_columnDelimiter": {
						"type": "String"
					},
					"cw_escapeChar": {
						"type": "String"
					},
					"cw_quoteChar": {
						"type": "String"
					},
					"cw_firstRowAsHeader": {
						"type": "Bool"
					},
					"cw_fileName": {
						"type": "Object"
					},
					"cw_folderPath": {
						"type": "Object"
					},
					"cw_fileSystem": {
						"type": "String"
					}
				},
				"folder": {
					"name": "MetadataDrivenCopyTask_5hq_20240705"
				},
				"annotations": [],
				"type": "DelimitedText",
				"typeProperties": {
					"location": {
						"type": "AzureBlobFSLocation",
						"fileName": {
							"value": "@dataset().cw_fileName",
							"type": "Expression"
						},
						"folderPath": {
							"value": "@dataset().cw_folderPath",
							"type": "Expression"
						},
						"fileSystem": {
							"value": "@dataset().cw_fileSystem",
							"type": "Expression"
						}
					},
					"columnDelimiter": {
						"value": "@dataset().cw_columnDelimiter",
						"type": "Expression"
					},
					"escapeChar": {
						"value": "@dataset().cw_escapeChar",
						"type": "Expression"
					},
					"firstRowAsHeader": {
						"value": "@dataset().cw_firstRowAsHeader",
						"type": "Expression"
					},
					"quoteChar": {
						"value": "@dataset().cw_quoteChar",
						"type": "Expression"
					}
				},
				"schema": []
			},
			"dependsOn": [
				"[concat(variables('factoryId'), '/linkedServices/lk_dl_cedc_2')]"
			]
		},
		{
			"name": "[concat(parameters('factoryName'), '/MetadataDrivenCopyTask_5hq_SourceDS')]",
			"type": "Microsoft.DataFactory/factories/datasets",
			"apiVersion": "2018-06-01",
			"properties": {
				"linkedServiceName": {
					"referenceName": "lk_dl_cedc_2",
					"type": "LinkedServiceReference"
				},
				"parameters": {
					"cw_columnDelimiter": {
						"type": "String"
					},
					"cw_escapeChar": {
						"type": "String"
					},
					"cw_quoteChar": {
						"type": "String"
					},
					"cw_firstRowAsHeader": {
						"type": "Bool"
					},
					"cw_fileName": {
						"type": "Object"
					},
					"cw_folderPath": {
						"type": "Object"
					},
					"cw_fileSystem": {
						"type": "String"
					}
				},
				"folder": {
					"name": "MetadataDrivenCopyTask_5hq_20240705"
				},
				"annotations": [],
				"type": "DelimitedText",
				"typeProperties": {
					"location": {
						"type": "AzureBlobFSLocation",
						"fileName": {
							"value": "@dataset().cw_fileName",
							"type": "Expression"
						},
						"folderPath": {
							"value": "@dataset().cw_folderPath",
							"type": "Expression"
						},
						"fileSystem": {
							"value": "@dataset().cw_fileSystem",
							"type": "Expression"
						}
					},
					"columnDelimiter": {
						"value": "@dataset().cw_columnDelimiter",
						"type": "Expression"
					},
					"escapeChar": {
						"value": "@dataset().cw_escapeChar",
						"type": "Expression"
					},
					"firstRowAsHeader": {
						"value": "@dataset().cw_firstRowAsHeader",
						"type": "Expression"
					},
					"quoteChar": {
						"value": "@dataset().cw_quoteChar",
						"type": "Expression"
					}
				},
				"schema": []
			},
			"dependsOn": [
				"[concat(variables('factoryId'), '/linkedServices/lk_dl_cedc_2')]"
			]
		},
		{
			"name": "[concat(parameters('factoryName'), '/MetadataDrivenCopyTask_axv_DestinationDS')]",
			"type": "Microsoft.DataFactory/factories/datasets",
			"apiVersion": "2018-06-01",
			"properties": {
				"linkedServiceName": {
					"referenceName": "lk_dl_cedc_2",
					"type": "LinkedServiceReference"
				},
				"parameters": {
					"cw_fileName": {
						"type": "Object"
					},
					"cw_folderPath": {
						"type": "Object"
					},
					"cw_fileSystem": {
						"type": "String"
					}
				},
				"folder": {
					"name": "MetadataDrivenCopyTask_axv_20240717"
				},
				"annotations": [],
				"type": "Parquet",
				"typeProperties": {
					"location": {
						"type": "AzureBlobFSLocation",
						"fileName": {
							"value": "@dataset().cw_fileName",
							"type": "Expression"
						},
						"folderPath": {
							"value": "@dataset().cw_folderPath",
							"type": "Expression"
						},
						"fileSystem": {
							"value": "@dataset().cw_fileSystem",
							"type": "Expression"
						}
					},
					"compressionCodec": "snappy"
				},
				"schema": []
			},
			"dependsOn": [
				"[concat(variables('factoryId'), '/linkedServices/lk_dl_cedc_2')]"
			]
		}
	]
}